DESCRIPTION.rst
MANIFEST.in
setup.py
tbltojson/__init__.py
tbltojson/tbltojson.py
tbltojson.egg-info/PKG-INFO
tbltojson.egg-info/SOURCES.txt
tbltojson.egg-info/dependency_links.txt
tbltojson.egg-info/entry_points.txt
tbltojson.egg-info/top_level.txt