Metadata-Version: 1.1
Name: tbltojson
Version: 0.0.3
Summary: convert mysql query output into json/yaml array
Home-page: https://github.com/tacodata/tbltojson
Author: Greg Fausak
Author-email: greg@tacodata.com
License: Apache Software License
Keywords: json yaml yml mysql table query output
Platform: UNKNOWN
Classifier: Development Status :: 3 - Alpha
Classifier: Intended Audience :: Developers
Classifier: Topic :: Software Development :: Build Tools
Classifier: License :: OSI Approved :: Apache Software License
Classifier: Programming Language :: Python :: 2
Classifier: Programming Language :: Python :: 2.6
Classifier: Programming Language :: Python :: 2.7
Classifier: Programming Language :: Python :: 3
Classifier: Programming Language :: Python :: 3.2
Classifier: Programming Language :: Python :: 3.3
Classifier: Programming Language :: Python :: 3.4
